lognflow/__init__.py
lognflow/lognflow.py
lognflow/logviewer.py
lognflow/loopprocessor.py
lognflow/multiprocessor.py
lognflow/plt_utils.py
lognflow/printprogress.py
lognflow/utils.py
lognflow-0.14.0.dist-info/licenses/AUTHORS.rst
lognflow-0.14.0.dist-info/licenses/LICENSE
lognflow-0.14.0.dist-info/METADATA
lognflow-0.14.0.dist-info/WHEEL
lognflow-0.14.0.dist-info/top_level.txt
lognflow-0.14.0.dist-info/RECORD
